MANIFEST.in
README.txt
RELEASE-VERSION
setup.py
version.py
fexpect.egg-info/PKG-INFO
fexpect.egg-info/SOURCES.txt
fexpect.egg-info/dependency_links.txt
fexpect.egg-info/namespace_packages.txt
fexpect.egg-info/not-zip-safe
fexpect.egg-info/requires.txt
fexpect.egg-info/top_level.txt
ilogue/__init__.py
ilogue/fexpect/__init__.py
ilogue/fexpect/api.py
ilogue/fexpect/internals.py
ilogue/fexpect/tests.py